gcodeBuddy/__init__.py
gcodeBuddy/arc.py
gcodeBuddy/base_classes.py
gcodeBuddy/fisnar.py
gcodeBuddy/marlin.py
gcodeBuddy/misc_functions.py
gcodeBuddy-1.1.1.dist-info/LICENSE.txt
gcodeBuddy-1.1.1.dist-info/METADATA
gcodeBuddy-1.1.1.dist-info/WHEEL
gcodeBuddy-1.1.1.dist-info/top_level.txt
gcodeBuddy-1.1.1.dist-info/RECORD
