Metadata-Version: 2.1
Name: gcodeBuddy
Version: 1.1.1
Summary: Python package used to write to, read from, and interpret g-code files
Home-page: https://gcodeBuddy.readthedocs.io/
Author: Spencer Bertram
Author-email: spenbert02@gmail.com
License: MIT
Platform: UNKNOWN
Classifier: License :: OSI Approved :: MIT License
Classifier: Programming Language :: Python
Classifier: Programming Language :: Python :: 3
Classifier: Programming Language :: Python :: 3.9
Classifier: Operating System :: OS Independent
License-File: LICENSE.txt
Requires-Dist: bs4
Requires-Dist: matplotlib
Requires-Dist: numpy
